{
  "titulo": "Los Sims 3",
  "plataforma": "Windows XP/Vista/7",
  "estado": "Sin-verificar",
  "genero": "Simulacion de vida",
  "desarrollador": "The Sims Studio",
  "distribuidor": "Electronic Arts",
  "ean": "",
  "descripcion": "Tercera entrega de la saga de simulación de vida. Introduce un mundo abierto donde los Sims pueden moverse libremente por la ciudad, nuevas herramientas de personalización, rasgos de personalidad y un sistema de deseos dinámico.",
  "incluye": [],
  "serie":"",
  "tags":[]
}
