{
  "titulo": "CSI: Las 3 Dimensiones del Asesinato",
  "plataforma": ["Windows 2000/XP"],
  "estado": "Sin-verificar",
  "genero": ["Aventura gráfica", "Investigación"],
  "desarrollador": ["Ubisoft", "Telltale Games"],
  "distribuidor": ["Ubisoft"],
  "ean": [],
  "descripcion": "Aventura gráfica basada en la serie de televisión CSI: Crime Scene Investigation. El jugador resuelve casos criminales utilizando técnicas forenses, análisis de pruebas y entrevistas a sospechosos, con gráficos 3D que recrean los escenarios de la serie.",
  "incluye": [],
  "serie": [],
  "tags": []
}
