{
  "titulo": "Tom Clancy's Splinter Cell: Pandora Tomorrow",
  "plataforma": ["Windows 98/ME/2000/XP"],
  "estado": "Sin-verificar",
  "genero": ["Acción", "Infiltración"],
  "desarrollador": ["Ubisoft Shanghai"],
  "distribuidor": ["Ubisoft"],
  "ean": [],
  "descripcion": "Segunda entrega de la saga Splinter Cell. El jugador controla al agente Sam Fisher en una misión de infiltración y espionaje internacional, con nuevas mecánicas de sigilo, gadgets avanzados y un innovador modo multijugador espía contra mercenarios.",
  "incluye": [],
  "serie": [],
  "tags": []
}
