{
  "titulo": "The Book of Unwritten Tales 2",
  "plataforma": ["Windows XP/Vista/7/8"],
  "estado": "Sin-verificar",
  "genero": ["Aventura gráfica", "Point and Click"],
  "desarrollador": ["KING Art Games"],
  "distribuidor": ["Nordic Games"],
  "ean": [],
  "descripcion": "Secuela de la aventura gráfica The Book of Unwritten Tales. Combina humor, referencias al mundo de la fantasía y puzzles clásicos de point and click, con varios personajes jugables y una historia cargada de guiños al género.",
  "incluye": [],
  "serie": [],
  "tags": []
}
