{
  "titulo": "Dungeons: The Dark Lord",
  "plataforma": "Windows XP SP2 / Vista / 7",
  "estado": "Sin‑verificar",
  "genero": "Estrategia / Simulación / RPG",
  "desarrollador": "Realmforge Studios",
  "distribuidor": "FX Interactive",
  "EAN": "8436010153566",
  "descripcion": "Secuela directa de Dungeons (2011), añade campaña completa con voces, modos multijugador para hasta 4 jugadores (Deathmatch, King of the Hill, Piñata y Survival), nuevas mazmorras, trampas y prestigios.",
  "incluye": ""
}
