{
  "titulo": "Age of Empires II: The Age of Kings",
  "plataforma": "Windows 95, Windows 98, Windows NT 4.0, Windows 2000, Mac OS (2001)",
  "estado": "Verificado",
  "genero": "Real-time strategy",
  "desarrollador": "Ensemble Studios",
  "distribuidor": "Microsoft",
  "ean": "",
  "descripcion": "Segunda entrega de la saga Age of Empires (1999). Guías diversas civilizaciones medievales desde la Edad Oscura hasta el Renacimiento a través de campañas históricas y multijugador. Incluye editor de escenarios y motor Genie. Lanzado originalmente para PC y adaptado posteriormente a Mac en 2001.",
  "incluye": []
}